{
	"configurations" : 
	[
		{
			"directories" : 
			[
				{
					"build" : ".",
					"jsonFile" : "directory-.-Debug-f5ebdc15457944623624.json",
					"minimumCMakeVersion" : 
					{
						"string" : "3.24"
					},
					"projectIndex" : 0,
					"source" : ".",
					"targetIndexes" : 
					[
						0
					]
				}
			],
			"name" : "Debug",
			"projects" : 
			[
				{
					"directoryIndexes" : 
					[
						0
					],
					"name" : "project2",
					"targetIndexes" : 
					[
						0
					]
				}
			],
			"targets" : 
			[
				{
					"directoryIndex" : 0,
					"id" : "project2::@6890427a1f51a3e7e1df",
					"jsonFile" : "target-project2-Debug-aaa0abc18e8d6b6ef1c3.json",
					"name" : "project2",
					"projectIndex" : 0
				}
			]
		}
	],
	"kind" : "codemodel",
	"paths" : 
	{
		"build" : "/home/zhzhzh/ClionProjects/project2/cmake-build-debug",
		"source" : "/home/zhzhzh/ClionProjects/project2"
	},
	"version" : 
	{
		"major" : 2,
		"minor" : 4
	}
}
